async_direct_redis/__init__.py
async_direct_redis/async_direct_redis.py
async_direct_redis/direct_redis.py
async_direct_redis/functions.py
async_direct_redis-0.3.1.dist-info/LICENSE
async_direct_redis-0.3.1.dist-info/METADATA
async_direct_redis-0.3.1.dist-info/WHEEL
async_direct_redis-0.3.1.dist-info/top_level.txt
async_direct_redis-0.3.1.dist-info/RECORD
