Metadata-Version: 2.1
Name: async-direct-redis
Version: 0.3.1
Summary: Fork of direct_redis with redis version bumped up to support asynchronous calls.
Home-page: https://github.com/shree-c/direct-redis-async
Author: Yonghee Cheon
Author-email: yonghee.cheon@gmail.com
License: MIT
Classifier: Programming Language :: Python :: 3
Classifier: License :: OSI Approved :: MIT License
Classifier: Operating System :: OS Independent
Requires-Python: >=3.4
License-File: LICENSE
Requires-Dist: redis ==5.0.1
